pyivxv/__init__.py
pyivxv/asn1/__init__.py
pyivxv/asn1/schemas.py
pyivxv/crypto/__init__.py
pyivxv/crypto/ciphertext.py
pyivxv/crypto/decryption_proof.py
pyivxv/crypto/drbg.py
pyivxv/crypto/exceptions.py
pyivxv/crypto/keys.py
pyivxv/crypto/zkp.py
pyivxv/encoding/__init__.py
pyivxv/encoding/ec_point.py
pyivxv/encoding/message.py
pyivxv/encoding/pem.py
pyivxv/math/__init__.py
pyivxv/math/ntheory.py
pyivxv-0.0.1a3.dist-info/licenses/LICENSE
pyivxv-0.0.1a3.dist-info/METADATA
pyivxv-0.0.1a3.dist-info/WHEEL
pyivxv-0.0.1a3.dist-info/top_level.txt
pyivxv-0.0.1a3.dist-info/RECORD
