Metadata-Version: 2.4
Name: pyivxv
Version: 0.0.1a3
Summary: Cryptographic recipes and primitives used in IVXV.
Author: takakv
License-Expression: MIT
Project-URL: homepage, https://github.com/takakv/pyivxv
Project-URL: source, https://github.com/takakv/pyivxv/
Project-URL: issues, https://github.com/takakv/pyivxv/issues
Classifier: Development Status :: 3 - Alpha
Classifier: Intended Audience :: Developers
Classifier: Programming Language :: Python :: 3
Classifier: Operating System :: OS Independent
Classifier: Topic :: Security :: Cryptography
Requires-Python: >=3.9
License-File: LICENSE
Requires-Dist: fastecdsa>=3.0.1
Requires-Dist: pyasn1>=0.6.1
Requires-Dist: pyasn1-modules>=0.4.2
Dynamic: license-file
